MANIFEST.in
distribute_setup.py
setup.py
src/django_exceptional.egg-info/PKG-INFO
src/django_exceptional.egg-info/SOURCES.txt
src/django_exceptional.egg-info/dependency_links.txt
src/django_exceptional.egg-info/top_level.txt
src/djexceptional/__init__.py
src/djexceptional/models.py
src/djexceptional/utils.py
src/djexceptional/tests/__init__.py
src/djexceptional/tests/memoize.py