Metadata-Version: 1.0
Name: django-exceptional
Version: 0.1.5
Summary: A Django client for Exceptional (getexceptional.com).
Home-page: http://github.com/zacharyvoase/django-exceptional
Author: Zachary Voase
Author-email: z@zacharyvoase.com
License: UNKNOWN
Platform: UNKNOWN
